{"cameraMode":{"drawMode":0,"name":"Shaded","section":"Shading Mode"},"sceneLighting":false,"audioPlay":false,"sceneViewState":{"m_AlwaysRefresh":false,"showFog":true,"showSkybox":false,"showFlares":true,"showImageEffects":true,"showParticleSystems":true,"showVisualEffectGraphs":true,"m_FxEnabled":true},"in2DMode":false,"pivot":{"x":4.891810894012451,"y":-4.065190315246582,"z":7.078007221221924},"rotation":{"x":0.10722830146551132,"y":0.8668805956840515,"z":-0.21213969588279725,"w":0.4381664991378784},"size":16.20976448059082,"orthographic":false}